{"moduleName":null,"summaries":[{"symbol":{"__symbol":0,"members":[]},"metadata":{"__symbolic":"function","parameters":["firstNumber","secondNumber"],"value":{"__symbolic":"binop","operator":"||","left":{"__symbolic":"pre","operator":"!","operand":{"__symbolic":"call","arguments":[{"__symbolic":"reference","name":"firstNumber"}]}},"right":{"__symbolic":"call","arguments":[{"__symbolic":"reference","name":"secondNumber"}]}}}}],"symbols":[{"__symbol":0,"name":"extendedFunc","filePath":"./util.module"}]}